{
    "title": "Программирование. Компиляторы и IDE для языка Си",
    "description": "Для того, чтобы писать программы на языке Си необходимо установить компилятор языка Си или IDE, поддерживающую язык Си. Список IDE и компиляторов для программирования на Си.",
    "keywords": "программирование, компилятор, компиляция, список компиляторов С, IDE, интегрированная среда разработки, список IDE с языком Си",
    "article_number": 1,
    "canonical_link": "https://youngcoder.ru/lessons/1/programming"
}